sysmon2df/Eula.txt
sysmon2df/README.md
sysmon2df/Sysmon.exe
sysmon2df/Sysmon64.exe
sysmon2df/Sysmon64a.exe
sysmon2df/__init__.py
sysmon2df/requirements.txt
sysmon2df/thirdparty.json
sysmon2df-0.10.dist-info/LICENSE.rst
sysmon2df-0.10.dist-info/METADATA
sysmon2df-0.10.dist-info/WHEEL
sysmon2df-0.10.dist-info/top_level.txt
sysmon2df-0.10.dist-info/RECORD
