Metadata-Version: 2.1
Name: sysmon2df
Version: 0.10
Summary: Captures Sysmon events and converts the output into a pandas DataFrames / CSV
Home-page: https://github.com/hansalemaos/sysmon2df
Author: Johannes Fischer
Author-email: aulasparticularesdealemaosp@gmail.com
License: MIT
Keywords: EVTX,csv,convert,pandas,sysmon
Classifier: Development Status :: 4 - Beta
Classifier: Programming Language :: Python :: 3 :: Only
Classifier: Programming Language :: Python :: 3.10
Classifier: Topic :: Software Development :: Libraries :: Python Modules
Classifier: Topic :: Utilities
License-File: LICENSE.rst
Requires-Dist: evtx2df
Requires-Dist: getfilenuitkapython
Requires-Dist: kthread-sleep
Requires-Dist: pandas
Requires-Dist: touchtouch
